LICENSE
MANIFEST.in
README.rst
setup.py
simplerpc.py
test_simplerpc.py
simplerpc.egg-info/PKG-INFO
simplerpc.egg-info/SOURCES.txt
simplerpc.egg-info/dependency_links.txt
simplerpc.egg-info/requires.txt
simplerpc.egg-info/top_level.txt